kafka2delta/__init__.py
kafka2delta/conftest.py
kafka2delta/config/__init__.py
kafka2delta/config/config.py
kafka2delta/stream/__init__.py
kafka2delta/stream/stream.py
kafka2delta/stream/test/__init__.py
kafka2delta/stream/test/stream_listener.py
kafka2delta/stream/test/stream_test.py
kafka2delta/udf/__init__.py
kafka2delta/udf/udf.py
kafka2delta/utils/__init__.py
kafka2delta/utils/utils.py
kafka2delta/utils/test/__init__.py
kafka2delta/utils/test/avro_schema.py
kafka2delta/utils/test/avro_test.py
kafka2delta-1.3.0.dist-info/licenses/LICENSE
kafka2delta-1.3.0.dist-info/METADATA
kafka2delta-1.3.0.dist-info/WHEEL
kafka2delta-1.3.0.dist-info/top_level.txt
kafka2delta-1.3.0.dist-info/RECORD
