Metadata-Version: 2.4
Name: kafka2delta
Version: 1.3.0
Summary: Stream Change Data Capture data from Kafka into Delta Tables using Spark StructuredStreaming.
Author-email: Sebastian Daberdaku <112859176+sdaberdaku@users.noreply.github.com>, Aleksander Duka <87473472+aleksanderduka@users.noreply.github.com>
Project-URL: Repository, https://github.com/sdaberdaku/kafka2delta.git
Project-URL: Issues, https://github.com/sdaberdaku/kafka2delta/issues
Keywords: CDC,Debezium,Kafka,Delta Lake,Spark,PostgreSQL
Classifier: Programming Language :: Python :: 3
Classifier: Programming Language :: Python :: 3.10
Classifier: Operating System :: OS Independent
Requires-Python: >=3.10
License-File: LICENSE
Requires-Dist: confluent-kafka<2.6.0,>=2.5.0
Requires-Dist: delta-spark<4.0.0,>=3.2.0
Requires-Dist: pyspark<4.0.0,>=3.5.1
Dynamic: license-file
